spicer/__init__.py
spicer/exceptions.py
spicer/kernels.py
spicer/kmaspice.py
spicer/spicer.py
spicer-0.6.0.dist-info/LICENSE
spicer-0.6.0.dist-info/METADATA
spicer-0.6.0.dist-info/WHEEL
spicer-0.6.0.dist-info/top_level.txt
spicer-0.6.0.dist-info/zip-safe
spicer-0.6.0.dist-info/RECORD
