Metadata-Version: 2.1
Name: spicer
Version: 0.6.0
Summary: Library to make SPICE a bit easier
Home-page: https://github.com/michaelaye/spicer
Author: K.-Michael Aye
Author-email: kmichael.aye@gmail.com
License: MIT license
Keywords: Solarsystem,planetaryscience,planets
Platform: UNKNOWN
Classifier: Development Status :: 2 - Pre-Alpha
Classifier: Intended Audience :: Developers
Classifier: License :: OSI Approved :: MIT License
Classifier: Natural Language :: English
Classifier: Programming Language :: Python :: 3
Classifier: Programming Language :: Python :: 3.7
Classifier: Programming Language :: Python :: 3 :: Only
Requires-Python: >=3.6, <4
Requires-Dist: spiceypy
Requires-Dist: tqdm
Requires-Dist: planetarypy (>=0.7)
Requires-Dist: astropy
Requires-Dist: urlpath
Requires-Dist: importlib-resources ; python_version < "3.9"
